odoo/addons/stock_no_negative/README.rst
odoo/addons/stock_no_negative/__init__.py
odoo/addons/stock_no_negative/__manifest__.py
odoo/addons/stock_no_negative/i18n/ar.po
odoo/addons/stock_no_negative/i18n/es.po
odoo/addons/stock_no_negative/i18n/fr.po
odoo/addons/stock_no_negative/i18n/pt.po
odoo/addons/stock_no_negative/i18n/pt_BR.po
odoo/addons/stock_no_negative/i18n/sl.po
odoo/addons/stock_no_negative/i18n/stock_no_negative.pot
odoo/addons/stock_no_negative/models/__init__.py
odoo/addons/stock_no_negative/models/product.py
odoo/addons/stock_no_negative/models/stock_location.py
odoo/addons/stock_no_negative/models/stock_quant.py
odoo/addons/stock_no_negative/readme/CONFIGURE.rst
odoo/addons/stock_no_negative/readme/CONTRIBUTORS.rst
odoo/addons/stock_no_negative/readme/DESCRIPTION.rst
odoo/addons/stock_no_negative/readme/HISTORY.rst
odoo/addons/stock_no_negative/readme/USAGE.rst
odoo/addons/stock_no_negative/static/description/icon.png
odoo/addons/stock_no_negative/static/description/index.html
odoo/addons/stock_no_negative/tests/__init__.py
odoo/addons/stock_no_negative/tests/test_stock_no_negative.py
odoo/addons/stock_no_negative/views/product_product_views.xml
odoo/addons/stock_no_negative/views/stock_location_views.xml
odoo12_addon_stock_no_negative-12.0.1.2.0.dist-info/METADATA
odoo12_addon_stock_no_negative-12.0.1.2.0.dist-info/WHEEL
odoo12_addon_stock_no_negative-12.0.1.2.0.dist-info/top_level.txt
odoo12_addon_stock_no_negative-12.0.1.2.0.dist-info/RECORD
